MANIFEST.in
README.md
setup.py
finsymbols/__init__.py
finsymbols/symbol_helper.py
finsymbols/symbols.py
finsymbols.egg-info/.DS_Store
finsymbols.egg-info/PKG-INFO
finsymbols.egg-info/SOURCES.txt
finsymbols.egg-info/dependency_links.txt
finsymbols.egg-info/requires.txt
finsymbols.egg-info/top_level.txt