Metadata-Version: 1.1
Name: finsymbols
Version: 1.2.0
Summary: Retrieves list of all symbols present in SP500, NASDAQ ,AMEX and NYSE
Home-page: http://skillachie.github.io/finsymbols/
Author: Dwayne V Campbell
Author-email: dwaynecampbell13 _at_ gmail.com
License: GNU LGPLv2+
Download-URL: http://pypi.python.org/pypi/finsymbols
Keywords: stocks,stockmarket,yahoo,finance,SP500,NASDAQ,AMEX,NYSE
Platform: UNKNOWN
Classifier: Development Status :: 4 - Beta
Classifier: Intended Audience :: Developers
Classifier: License :: OSI Approved :: GNU Lesser General Public License v2 or later (LGPLv2+)
Classifier: Topic :: Software Development :: Libraries :: Python Modules
Classifier: Topic :: Office/Business :: Financial :: Investment
